<?xml version="1.0" encoding="UTF-8"?>
<entry xmlns="http://www.w3.org/2005/Atom" xmlns:dcterms="http://purl.org/dc/terms" xmlns:xhtml="http://www.w3.org/1999/xhtml">
  <title>Romeo y Julieta</title>
  <id>urn:book:c3c80473-40ed-4a8c-84be-6448da017b3c</id>
  <updated>2015-03-27T01:53:52Z</updated>
  <link href="./861630a3%40book_260.xml" type="application/atom+xml;type=entry;profile=opds-catalog" rel="self" title="Romeo y Julieta" />
  <link href="../8f6fb6ff@index.xml" type="application/atom+xml;profile=opds-catalog;kind=navigation" rel="start" title="Biblioteca de Calibre de CJ" />
  <link href="../8f6fb6ff@index.xml" type="application/atom+xml;profile=opds-catalog;kind=navigation" rel="breadcrumb" title="Biblioteca de Calibre de CJ" />
  <link href="../8f6fb6ff%40authorlist/e8e4356e%40authorlist_Page_2.xml" type="application/atom+xml;profile=opds-catalog;kind=navigation" rel="breadcrumb" title="Autores" />
  <link href="861630a3@book_260_cover.jpg" type="image/jpg" rel="http://opds-spec.org/image" />
  <link href="../8f6fb6ff@book_0/861630a3@book_260_c2o_thumbnail.jpg" type="image/jpg" rel="http://opds-spec.org/image/thumbnail" />
  <link href="https://dl.dropboxusercontent.com/u/13030543/ocabiblio/William%20Shakespeare/Romeo%20y%20Julieta%20%28260%29/Romeo%20y%20Julieta%20-%20William%20Shakespeare.epub" type="application/epub+zip" rel="http://opds-spec.org/acquisition" title="Descargar este libro como EPUB" />
  <author>
    <name>William Shakespeare</name>
    <uri>../8f6fb6ff@author_0/beacae01@author_97_Page_1.xml</uri>
  </author>
  <published>1596-12-31T11:00:00Z</published>
  <dcterms:language>es</dcterms:language>
  <dcterms:publisher>ePubLibre</dcterms:publisher>
  <category term="Teatro" />
  <category term="Drama" />
  <category term="Lang:es" />
  <content type="text/html">
    <p>
      <strong>Rating:</strong>
      Sin puntuación
    </p>
    <p>
      <strong>Etiquetas:</strong>
      Teatro, Drama, Lang:es
    </p>
    <p>
      <strong>Published:</strong>
      31 de diciembre de 1596
    </p>
    <p>
      <strong>Sumario:</strong>
    </p>
    <p xmlns="">La historia de Romeo y Julieta tiene antecedentes en la
    mitología y literatura griegas y en algunas leyendas
    medievales. Durante los siglos XV y XVI fue objeto de
    múltiples versiones, pero fue Shakespeare quien le
    infundió una pasión y un dramatismo inéditos
    hasta entonces y que han contribuido a mantener la leyenda en
    la memoria colectiva. En Verona, dos jóvenes enamorados,
    de dos familias enemigas, son víctimas de una
    situación de odio y violencia que ni desean ni pueden
    remediar. Romeo, recién casado en secreto con Julieta,
    mata al primo de ésta. A partir de ahí Shakespeare
    desencadena la tragedia y precipita los acontecimientos,
    guiados por el azar y la fatalidad. Ángel-Luis Pujante
    destaca la fuerza poética y retórica de Romeo y
    Julieta: los juegos de palabras, la coexistencia de prosa y
    verso, de lo culto y lo coloquial, de lo lírico y lo
    dramático contribuyen a intensificar los contrastes de la
    acción. Clara Calvo ofrece una rica documentación
    complementaria que ayuda a enriquecer la lectura de esta obra
    capital de la literatura universal.</p>
  </content>
  <link href="../8f6fb6ff%40author_0/beacae01%40author_97_Page_1.xml" type="application/atom+xml;profile=opds-catalog;kind=navigation" rel="related" title="Libros de William Shakespeare" />
  <link href="http://www.goodreads.com/book/title/Romeo%20y%20Julieta" type="text/html" rel="related" title="Este libro en Goodreads" />
  <link href="http://es.wikipedia.org/wiki/Romeo%20y%20Julieta" type="text/html" rel="related" title="Este libro en Wikipedia" />
  <link href="http://www.librarything.com/title/Romeo%20y%20Julieta%20William%20Shakespeare" type="text/html" rel="related" title="Este libro en LibraryThing" />
  <link href="http://www.amazon.com/gp/search/ref=sr_adv_b/?search-alias=stripbooks&amp;unfiltered=1&amp;sort=relevanceexprank&amp;field-title=Romeo%20y%20Julieta&amp;field-author=William%20Shakespeare" type="text/html" rel="related" title="Este libro en Amazon" />
  <link href="http://www.goodreads.com/book/author/William%20Shakespeare" type="text/html" rel="related" title="William Shakespeare en Goodreads" />
  <link href="http://es.wikipedia.org/wiki/William%20Shakespeare" type="text/html" rel="related" title="William Shakespeare en Wikipedia" />
  <link href="http://www.librarything.com/author/ShakespeareWilliam" type="text/html" rel="related" title="William Shakespeare en LibraryThing" />
  <link href="http://www.amazon.com/gp/search/ref=sr_adv_b/?search-alias=stripbooks&amp;unfiltered=1&amp;sort=relevanceexprank&amp;field-author=William%20Shakespeare" type="text/html" rel="related" title="William Shakespeare en Amazon" />
  <link href="http://www.isfdb.org/cgi-bin/ea.cgi?William%20Shakespeare" type="text/html" rel="related" title="William Shakespeare en ISFDB" />
</entry>

